wlogger/__init__.py
wlogger/authenticate.py
wlogger/engine.py
wlogger/log.py
wlogger/release.py
wlogger/test.py
wlogger/utils/__init__.py
wlogger/utils/cryptex.py
wlogger-0.1.1.dist-info/DESCRIPTION.rst
wlogger-0.1.1.dist-info/METADATA
wlogger-0.1.1.dist-info/RECORD
wlogger-0.1.1.dist-info/WHEEL
wlogger-0.1.1.dist-info/entry_points.txt
wlogger-0.1.1.dist-info/metadata.json
wlogger-0.1.1.dist-info/top_level.txt
