Metadata-Version: 2.0
Name: wlogger
Version: 0.1.1
Summary: Minimalistic command-line progress tracker.
Home-page: https://github.com/kumarkrishna/wlogger
Author: Kumar Krishna Agrawal
Author-email: kumarkrishna.iitkgp@gmail.com
License: Apache License
Keywords: wlogger work logger todo project reminder
Platform: UNKNOWN
Requires-Dist: argcomplete
Requires-Dist: argparse
Requires-Dist: markdown
